bazinga_cli/__init__.py
bazinga_cli/_version.py
bazinga_cli/security.py
bazinga_cli/telemetry.py
bazinga_cli/hooks/bazinga-compact-recovery.ps1
bazinga_cli/hooks/bazinga-compact-recovery.sh
bazinga_cli/templates/batch_processing.md
bazinga_cli/templates/completion_report.md
bazinga_cli/templates/developer_speckit.md
bazinga_cli/templates/investigation_loop.md
bazinga_cli/templates/logging_pattern.md
bazinga_cli/templates/merge_workflow.md
bazinga_cli/templates/message_templates.md
bazinga_cli/templates/pm_autonomy.md
bazinga_cli/templates/pm_bazinga_validation.md
bazinga_cli/templates/pm_output_format.md
bazinga_cli/templates/pm_planning_steps.md
bazinga_cli/templates/pm_routing.md
bazinga_cli/templates/pm_speckit.md
bazinga_cli/templates/pm_task_classification.md
bazinga_cli/templates/prompt_building.md
bazinga_cli/templates/qa_speckit.md
bazinga_cli/templates/response_parsing.md
bazinga_cli/templates/shutdown_protocol.md
bazinga_cli/templates/tech_lead_speckit.md
bazinga_cli/templates/orchestrator/clarification_flow.md
bazinga_cli/templates/orchestrator/phase_parallel.md
bazinga_cli/templates/orchestrator/phase_simple.md
bazinga_cli/templates/orchestrator/scope_validation.md
bazinga_cli/templates/specializations/00-MASTER-INDEX.md
bazinga_cli/templates/specializations/01-languages/bash-shell.md
bazinga_cli/templates/specializations/01-languages/cpp.md
bazinga_cli/templates/specializations/01-languages/csharp.md
bazinga_cli/templates/specializations/01-languages/elixir.md
bazinga_cli/templates/specializations/01-languages/go.md
bazinga_cli/templates/specializations/01-languages/java.md
bazinga_cli/templates/specializations/01-languages/kotlin.md
bazinga_cli/templates/specializations/01-languages/php.md
bazinga_cli/templates/specializations/01-languages/python.md
bazinga_cli/templates/specializations/01-languages/ruby.md
bazinga_cli/templates/specializations/01-languages/rust.md
bazinga_cli/templates/specializations/01-languages/scala.md
bazinga_cli-1.2.3.dist-info/METADATA
bazinga_cli-1.2.3.dist-info/WHEEL
bazinga_cli-1.2.3.dist-info/entry_points.txt
bazinga_cli-1.2.3.dist-info/licenses/LICENSE
bazinga_cli-1.2.3.dist-info/RECORD
