Metadata-Version: 2.4
Name: bazinga-cli
Version: 1.2.3
Summary: BAZINGA CLI - A sophisticated multi-agent orchestration system for Claude Code
Project-URL: Homepage, https://github.com/mehdic/bazinga
Project-URL: Repository, https://github.com/mehdic/bazinga
Project-URL: Documentation, https://github.com/mehdic/bazinga#readme
Project-URL: Issues, https://github.com/mehdic/bazinga/issues
Author-email: Mehdi C <mehdic@users.noreply.github.com>
License: MIT
License-File: LICENSE
Keywords: ai,claude,cli,multi-agent,orchestration
Classifier: Development Status :: 4 - Beta
Classifier: Intended Audience :: Developers
Classifier: License :: OSI Approved :: MIT License
Classifier: Programming Language :: Python :: 3
Classifier: Programming Language :: Python :: 3.11
Classifier: Programming Language :: Python :: 3.12
Requires-Python: >=3.11
Requires-Dist: httpx[socks]>=0.25.0
Requires-Dist: platformdirs>=3.0.0
Requires-Dist: pyyaml>=6.0.0
Requires-Dist: rich>=13.0.0
Requires-Dist: typer>=0.9.0
Provides-Extra: dev
Requires-Dist: pytest-cov>=4.1.0; extra == 'dev'
Requires-Dist: pytest-mock>=3.11.0; extra == 'dev'
Requires-Dist: pytest-timeout>=2.1.0; extra == 'dev'
Requires-Dist: pytest>=7.4.0; extra == 'dev'
